kbodata/__init__.py
kbodata/get/__init__.py
kbodata/get/game.py
kbodata/get/schedule.py
kbodata/load/__init__.py
kbodata/load/batter.py
kbodata/load/pitcher.py
kbodata/load/scoreboard.py
kbodata/parser/__init__.py
kbodata/parser/batter.py
kbodata/parser/config.ini
kbodata/parser/html.py
kbodata/parser/page.py
kbodata/parser/pitcher.py
kbodata/parser/schedule.py
kbodata/parser/scoreboard.py
kbodata/parser/util.py
kbodata-0.2.3.dist-info/LICENSE
kbodata-0.2.3.dist-info/METADATA
kbodata-0.2.3.dist-info/WHEEL
kbodata-0.2.3.dist-info/RECORD
