Metadata-Version: 2.1
Name: kbodata
Version: 0.2.3
Summary: Scraping Korea Baseball Game information
Home-page: https://github.com/Hyeonji-Ryu/kbo-data
License: MIT
Author: Hyeonji-Ryu
Author-email: dev.bearabbit@gmail.com
Requires-Python: >=3.9.0,<4.0.0
Classifier: License :: OSI Approved :: MIT License
Classifier: Programming Language :: Python :: 3
Classifier: Programming Language :: Python :: 3.9
Classifier: Programming Language :: Python :: 3.10
Classifier: Programming Language :: Python :: 3.11
Classifier: Programming Language :: Python :: 3.12
Requires-Dist: bs4 (>=0.0.2,<0.0.3)
Requires-Dist: lxml (>=5.2.2,<6.0.0)
Requires-Dist: pandas (>=2.2.2,<3.0.0)
Requires-Dist: requests (>=2.31.0,<3.0.0)
Requires-Dist: selenium (>=4.21.0,<5.0.0)
Requires-Dist: tqdm (>=4.66.4,<5.0.0)
Project-URL: Documentation, https://github.com/Hyeonji-Ryu/kbo-data/tree/main/docs
Project-URL: Repository, https://github.com/Hyeonji-Ryu/kbo-data
